sam/__init__.py
sam/__main__.py
sam/_version.py
sam/bot.py
sam/config.py
sam/redis_utils.py
sam/slack.py
opensam-0.1.4.dist-info/entry_points.txt
opensam-0.1.4.dist-info/licenses/LICENSE
opensam-0.1.4.dist-info/WHEEL
opensam-0.1.4.dist-info/METADATA
opensam-0.1.4.dist-info/RECORD
