Metadata-Version: 2.4
Name: OpenSam
Version: 0.1.4
Summary: A GPT based slack bot trained to specific personalities and use cases.
Keywords: GPT,AI,Slack,OpenAI,bot
Author-email: Johannes Maron <johannes@maron.family>
Requires-Python: >=3.11
Classifier: Development Status :: 2 - Pre-Alpha
Classifier: Programming Language :: Python
Classifier: Environment :: Web Environment
Classifier: Intended Audience :: Developers
Classifier: License :: OSI Approved :: BSD License
Classifier: Operating System :: OS Independent
Classifier: Programming Language :: Python
Classifier: Topic :: Software Development
Classifier: Topic :: Communications :: Chat
Classifier: Topic :: Internet :: WWW/HTTP
Classifier: Topic :: Communications :: Email
Classifier: Topic :: Games/Entertainment :: Role-Playing
Classifier: Topic :: Multimedia :: Sound/Audio :: Conversion
Classifier: Topic :: Multimedia :: Sound/Audio :: Speech
Classifier: Topic :: Office/Business
Classifier: Topic :: Office/Business :: Groupware
Classifier: Topic :: Scientific/Engineering :: Artificial Intelligence
Classifier: Topic :: Scientific/Engineering :: Human Machine Interfaces
Classifier: Topic :: Text Processing :: Markup :: Markdown
Classifier: Programming Language :: Python :: 3
Classifier: Programming Language :: Python :: 3 :: Only
Classifier: Programming Language :: Python :: 3.11
Classifier: Programming Language :: Python :: 3.12
License-File: LICENSE
Requires-Dist: aiohttp
Requires-Dist: httpx
Requires-Dist: click
Requires-Dist: redis
Requires-Dist: slack-bolt
Requires-Dist: openai>=1.21.0
Requires-Dist: sentry-sdk
Requires-Dist: pydoc-markdown ; extra == "docs"
Requires-Dist: mkdocs-material ; extra == "docs"
Requires-Dist: pymdown-extensions ; extra == "docs"
Requires-Dist: pre-commit==4.2.0 ; extra == "lint"
Requires-Dist: ruff==0.12.0 ; extra == "lint"
Requires-Dist: pytest ; extra == "test"
Requires-Dist: pytest-asyncio ; extra == "test"
Requires-Dist: pytest-cov ; extra == "test"
Requires-Dist: pytest-env ; extra == "test"
Requires-Dist: respx ; extra == "test"
Project-URL: Changelog, https://github.com/voiio/Sam/releases
Project-URL: Documentation, https://code.voiio.de/Sam/
Project-URL: Project-URL, https://github.com/voiio/Sam/
Provides-Extra: docs
Provides-Extra: lint
Provides-Extra: test
